ions/__init__.py
ions/calculators.py
ions/data.py
ions/decorator.py
ions/potential.py
ions/utils.py
ions/data/Li2O_mp-1960.cif
ions/data/bvparam_1991.yaml
ions/data/bvparams2020-average.json
ions/data/bvparams2020-average.pickle
ions/data/bvparams_averaged2020.csv
ions/data/bvparm2020.cif
ions/data/bvparm2020_edit.txt
ions/data/bvse_data.json
ions/data/bvse_data.pickle
ions/data/elneg_data.json
ions/data/icsd_bv.yaml
ions/data/icsd_bv_data.json
ions/data/quantum_n.pkl
ions/data/shannon-data-crystal.json
ions/data/shannon-data-crystal.pickle
ions/data/shannon-data-ionic.json
ions/data/shannon-data-ionic.pickle
ions/data/shannon-radii.json
ions/data/shannon-radii.pickle
ions/featurizers/__init__.py
ions/featurizers/_edge_featurizer.py
ions/featurizers/_structure_featurizer.py
ions/geom/__init__.py
ions/geom/box.py
ions/geom/edge.py
ions/geom/utils.py
ions/tools/__init__.py
ions/tools/percolator.py
ions/tools/saddle_finder.py
ions-0.4.1.dist-info/LICENSE
ions-0.4.1.dist-info/METADATA
ions-0.4.1.dist-info/WHEEL
ions-0.4.1.dist-info/top_level.txt
ions-0.4.1.dist-info/zip-safe
ions-0.4.1.dist-info/RECORD
