Metadata-Version: 2.1
Name: ions
Version: 0.4.1
Summary: A python library for studying ionic conductors
Home-page: https://github.com/dembart/ions
Author: Artem Dembitskiy
Author-email: art.dembitskiy@gmail.com
License: MIT
Keywords: Li-ion,barrier,activation,percolation,ion,ions,crystal,bvse,bvel,neb
Platform: UNKNOWN
Classifier: Programming Language :: Python :: 3.6
Classifier: Programming Language :: Python :: 3.7
Classifier: Programming Language :: Python :: 3.8
Classifier: Programming Language :: Python :: 3.9
Classifier: Programming Language :: Python :: 3.10
Classifier: Programming Language :: Python :: 3.11
Classifier: License :: OSI Approved :: MIT License
Classifier: Operating System :: OS Independent
License-File: LICENSE
Requires-Dist: ase
Requires-Dist: numpy
Requires-Dist: spglib
Requires-Dist: networkx
Requires-Dist: scipy
Requires-Dist: pymatgen
